.DS_Store
sci_analysis/__init__.py
sci_analysis/analysis/__init__.py
sci_analysis/analysis/base.py
sci_analysis/analysis/comparison.py
sci_analysis/analysis/exc.py
sci_analysis/analysis/hypo_tests.py
sci_analysis/analysis/stats.py
sci_analysis/data/__init__.py
sci_analysis/data/categorical.py
sci_analysis/data/data.py
sci_analysis/data/data_operations.py
sci_analysis/data/numeric.py
sci_analysis/graphs/__init__.py
sci_analysis/graphs/base.py
sci_analysis/graphs/categorical.py
sci_analysis/graphs/vector.py
sci_analysis/preferences/__init__.py
sci_analysis/preferences/preferences.py
sci_analysis/test/__init__.py
sci_analysis/test/base.py
sci_analysis/test/test_analyze.py
sci_analysis/test/test_anova.py
sci_analysis/test/test_cat_statistics.py
sci_analysis/test/test_categorical.py
sci_analysis/test/test_correlation.py
sci_analysis/test/test_data_operations.py
sci_analysis/test/test_determine_analysis_type.py
sci_analysis/test/test_equalvariance.py
sci_analysis/test/test_graph_boxplots.py
sci_analysis/test/test_graph_frequency.py
sci_analysis/test/test_graph_groupscatter.py
sci_analysis/test/test_graph_histo.py
sci_analysis/test/test_graph_scatter.py
sci_analysis/test/test_groupcorrelation.py
sci_analysis/test/test_grouplinregress.py
sci_analysis/test/test_groupstatistics.py
sci_analysis/test/test_kruskal.py
sci_analysis/test/test_kstest.py
sci_analysis/test/test_linregress.py
sci_analysis/test/test_mannwhitney.py
sci_analysis/test/test_normtest.py
sci_analysis/test/test_statistics.py
sci_analysis/test/test_ttest.py
sci_analysis/test/test_twosampleks.py
sci_analysis/test/test_vector.py
sci_analysis-2.2.1.dist-info/LICENSE
sci_analysis-2.2.1.dist-info/METADATA
sci_analysis-2.2.1.dist-info/WHEEL
sci_analysis-2.2.1.dist-info/top_level.txt
sci_analysis-2.2.1.dist-info/RECORD
